{
  "format_version": "1.26.0",
  "minecraft:block": {
    "description": {
      "identifier": "minersdelight:gossypium",
      "menu_category": { "category": "nature" }
    },
    "components": {
      "minecraft:destructible_by_mining": { "seconds_to_destroy": 0.2 },
      "minecraft:destructible_by_explosion": { "explosion_resistance": 0.2 },
      "minecraft:geometry": "minecraft:geometry.cross",
      "minecraft:material_instances": {
        "*": { "texture": "gossypium", "render_method": "alpha_test" }
      },
      "minecraft:placement_filter": {
        "conditions": [
          {
            "block_filter": ["minecraft:dirt","minecraft:grass_block","minecraft:podzol","minecraft:coarse_dirt","minecraft:rooted_dirt"],
            "allowed_faces": ["up"]
          }
        ]
      },
      "minecraft:light_dampening": 0,
      "minecraft:flammable": false,
      "minecraft:loot": "loot_tables/minersdelight/blocks/gossypium.json",
      "minecraft:flower_pottable": {},
      "minecraft:embedded_visual": {
        "geometry": "geometry.cross_crop_pot",
        "material_instances": {
          "*": {
            "texture": "gossypium",
            "render_method": "alpha_test",
            "ambient_occlusion": false,
            "face_dimming": false
          }
        }
      }
    }
  }
}